hnswlib-stubs/METADATA.toml
hnswlib-stubs/__init__.pyi
hnswlib-stubs/py.typed
types_hnswlib-0.8.0.20250227.dist-info/LICENSE
types_hnswlib-0.8.0.20250227.dist-info/METADATA
types_hnswlib-0.8.0.20250227.dist-info/WHEEL
types_hnswlib-0.8.0.20250227.dist-info/top_level.txt
types_hnswlib-0.8.0.20250227.dist-info/RECORD
